azure_debrepo/__init__.py
azure_debrepo/__main__.py
azure_debrepo/azure_storage.py
azure_debrepo/cli.py
azure_debrepo/gpg.py
azure_debrepo/lib.py
azure_debrepo/packages.py
azure_debrepo/release.py
azure_debrepo-0.0.2.dist-info/METADATA
azure_debrepo-0.0.2.dist-info/WHEEL
azure_debrepo-0.0.2.dist-info/top_level.txt
azure_debrepo-0.0.2.dist-info/RECORD
