Metadata-Version: 2.1
Name: azure-debrepo
Version: 0.0.2
Summary: Basic management of Debian packages repository in Azure blob storage
Home-page: UNKNOWN
Author: UNKNOWN
Author-email: UNKNOWN
License: UNKNOWN
Platform: UNKNOWN
